gptmem/__init__.py
gptmem/memory.py
gptmemory/__init__.py
gptmemory/memory.py
gptmem-0.0.2.dist-info/LICENSE
gptmem-0.0.2.dist-info/METADATA
gptmem-0.0.2.dist-info/WHEEL
gptmem-0.0.2.dist-info/top_level.txt
gptmem-0.0.2.dist-info/RECORD
