Metadata-Version: 2.1
Name: gptmem
Version: 0.0.2
Summary: Memory management system to enhance AI agents with personalized, context-aware responses
Home-page: https://github.com/assafelovic/gpt-memory
Author: Assaf Elovic
Author-email: assaf.elovic@gmail.com
License: Apache License 2.0
Classifier: Programming Language :: Python :: 3
Classifier: License :: OSI Approved :: Apache Software License
Classifier: Operating System :: OS Independent
Requires-Python: >=3.10
License-File: LICENSE
Requires-Dist: openai
